emt_madrid/__init__.py
emt_madrid/const.py
emt_madrid/emt_api.py
emt_madrid/parser.py
emt_madrid-0.0.3.dist-info/METADATA
emt_madrid-0.0.3.dist-info/WHEEL
emt_madrid-0.0.3.dist-info/licenses/LICENSE
emt_madrid-0.0.3.dist-info/RECORD
