Metadata-Version: 2.1
Name: emt_madrid
Version: 0.0.3
Summary: Python wrapper for the Madrid EMT (Empresa Municipal de Transportes) API
Project-URL: Homepage, https://github.com/fermartv/EMTMadrid
Project-URL: Bug Tracker, https://github.com/fermartv/EMTMadrid/issues
License-File: LICENSE
Classifier: License :: OSI Approved :: GNU General Public License v3 (GPLv3)
Classifier: Operating System :: OS Independent
Classifier: Programming Language :: Python :: 3
Requires-Python: >=3.7
Requires-Dist: aiohttp>=3.8.4
Requires-Dist: async-timeout>=4.0.2
